torrentfile/__init__.py
torrentfile/__main__.py
torrentfile/cli.py
torrentfile/commands.py
torrentfile/edit.py
torrentfile/hasher.py
torrentfile/interactive.py
torrentfile/mixins.py
torrentfile/rebuild.py
torrentfile/recheck.py
torrentfile/torrent.py
torrentfile/utils.py
torrentfile/version.py
torrentfile-0.9.2.dist-info/LICENSE
torrentfile-0.9.2.dist-info/METADATA
torrentfile-0.9.2.dist-info/WHEEL
torrentfile-0.9.2.dist-info/entry_points.txt
torrentfile-0.9.2.dist-info/top_level.txt
torrentfile-0.9.2.dist-info/RECORD
