Metadata-Version: 2.1
Name: torrentfile
Version: 0.9.2
Summary: Terminal based command line tool for creating Bittorrent files.
Author-email: alexpdev <alexpdev@pm.me>
Project-URL: homepage, https://github.com/alexpdev/torrentfile
Project-URL: repository, https://github.com
Project-URL: documentation, https://alexpdev.github.io/torrentfile
Project-URL: changelog, https://alexpdev.github.io/torrentfile/changelog/
Project-URL: issues, https://github.com/alexpdev/torrentfile/issues
Keywords: Bittorrent,torrent,bittorrent-metafiles,CLI,torrentfile
Classifier: Environment :: Console
Classifier: Development Status :: 4 - Beta
Classifier: Operating System :: OS Independent
Classifier: Programming Language :: Python
Classifier: Programming Language :: Python :: 3
Classifier: Programming Language :: Python :: 3.6
Classifier: Programming Language :: Python :: 3.7
Classifier: Programming Language :: Python :: 3.8
Classifier: Programming Language :: Python :: 3.9
Classifier: Programming Language :: Python :: 3.10
Classifier: Programming Language :: Python :: 3.11
Classifier: Programming Language :: Python :: 3 :: Only
Classifier: Intended Audience :: End Users/Desktop
Classifier: Intended Audience :: Developers
Classifier: Topic :: Utilities
Classifier: Topic :: Software Development :: Libraries :: Python Modules
Classifier: License :: OSI Approved :: Apache Software License
Requires-Python: >=3.6
License-File: LICENSE
Requires-Dist: pyben
